hqchart/HQChartPy2.pyd
hqchart/__init__.py
hqchart/hqchartpy2_fast.py
hqchart/hqchartpy2_pandas.py
hqchart/libcrypto-1_1-x64.dll
hqchart/libssl-1_1-x64.dll
hqchart-1.0.11.dist-info/METADATA
hqchart-1.0.11.dist-info/WHEEL
hqchart-1.0.11.dist-info/top_level.txt
hqchart-1.0.11.dist-info/RECORD
